obia/__init__.py
obia/classification/__init__.py
obia/classification/classify.py
obia/handlers/__init__.py
obia/handlers/geotif.py
obia/segmentation/__init__.py
obia/segmentation/segment.py
obia/segmentation/segment_boundaries.py
obia/segmentation/segment_statistics.py
obia/utils/__init__.py
obia/utils/image.py
obia/utils/tiling.py
obia/utils/utils.py
obia-0.1.3.dist-info/LICENSE
obia-0.1.3.dist-info/METADATA
obia-0.1.3.dist-info/WHEEL
obia-0.1.3.dist-info/top_level.txt
obia-0.1.3.dist-info/RECORD
